keyrings/onepassword/__init__.py
keyrings/onepassword/credential.py
keyrings/onepassword/keyring.py
keyrings/onepassword/py.typed
keyrings/onepassword/version.py
keyrings_onepassword-0.4.0.dist-info/LICENSE
keyrings_onepassword-0.4.0.dist-info/METADATA
keyrings_onepassword-0.4.0.dist-info/WHEEL
keyrings_onepassword-0.4.0.dist-info/entry_points.txt
keyrings_onepassword-0.4.0.dist-info/RECORD
