Metadata-Version: 2.3
Name: keyrings.onepassword
Version: 0.4.0
Summary: 
Author: RISQ Capital
Author-email: dev@risqcapital.com
Requires-Python: >=3.11
Classifier: Programming Language :: Python :: 3
Classifier: Programming Language :: Python :: 3.11
Classifier: Programming Language :: Python :: 3.12
Classifier: Programming Language :: Python :: 3.13
Requires-Dist: keyring (>=25.6.0,<26.0.0)
Requires-Dist: onepassword-sdk (>=0.1.5,<0.2.0)
